ShujuKexueSixiangChuyiFix1/README.md
ShujuKexueSixiangChuyiFix1/__init__.py
ShujuKexueSixiangChuyiFix1/__main__.py
ShujuKexueSixiangChuyiFix1/file.epub
ShujuKexueSixiangChuyiFix1/index.html
ShujuKexueSixiangChuyiFix1/css/__init__.py
ShujuKexueSixiangChuyiFix1/css/annotations.css
ShujuKexueSixiangChuyiFix1/css/main.css
ShujuKexueSixiangChuyiFix1/css/normalize.css
ShujuKexueSixiangChuyiFix1/css/popup.css
ShujuKexueSixiangChuyiFix1/font/__init__.py
ShujuKexueSixiangChuyiFix1/font/fontello.eot
ShujuKexueSixiangChuyiFix1/font/fontello.svg
ShujuKexueSixiangChuyiFix1/font/fontello.ttf
ShujuKexueSixiangChuyiFix1/font/fontello.woff
ShujuKexueSixiangChuyiFix1/img/__init__.py
ShujuKexueSixiangChuyiFix1/img/annotator-glyph-sprite.png
ShujuKexueSixiangChuyiFix1/img/annotator-icon-sprite.png
ShujuKexueSixiangChuyiFix1/img/apple-touch-icon.png
ShujuKexueSixiangChuyiFix1/img/cancelfullscreen.png
ShujuKexueSixiangChuyiFix1/img/close.png
ShujuKexueSixiangChuyiFix1/img/fullscreen.png
ShujuKexueSixiangChuyiFix1/img/loader.gif
ShujuKexueSixiangChuyiFix1/img/menu-icon.png
ShujuKexueSixiangChuyiFix1/img/save.png
ShujuKexueSixiangChuyiFix1/img/saved.png
ShujuKexueSixiangChuyiFix1/img/settings-s.png
ShujuKexueSixiangChuyiFix1/img/settings.png
ShujuKexueSixiangChuyiFix1/img/star.png
ShujuKexueSixiangChuyiFix1/js/__init__.py
ShujuKexueSixiangChuyiFix1/js/epub.js
ShujuKexueSixiangChuyiFix1/js/epub.min.js
ShujuKexueSixiangChuyiFix1/js/epub.min.map
ShujuKexueSixiangChuyiFix1/js/hooks.min.js
ShujuKexueSixiangChuyiFix1/js/hooks.min.map
ShujuKexueSixiangChuyiFix1/js/reader.js
ShujuKexueSixiangChuyiFix1/js/reader.js.map
ShujuKexueSixiangChuyiFix1/js/reader.min.js
ShujuKexueSixiangChuyiFix1/js/reader.min.map
ShujuKexueSixiangChuyiFix1/js/hooks/__init__.py
ShujuKexueSixiangChuyiFix1/js/hooks/extensions/__init__.py
ShujuKexueSixiangChuyiFix1/js/hooks/extensions/highlight.js
ShujuKexueSixiangChuyiFix1/js/libs/__init__.py
ShujuKexueSixiangChuyiFix1/js/libs/jquery.min.js
shuju_kexue_sixiang_chuyi_fix1-2025.3.25.1.dist-info/METADATA
shuju_kexue_sixiang_chuyi_fix1-2025.3.25.1.dist-info/WHEEL
shuju_kexue_sixiang_chuyi_fix1-2025.3.25.1.dist-info/entry_points.txt
shuju_kexue_sixiang_chuyi_fix1-2025.3.25.1.dist-info/top_level.txt
shuju_kexue_sixiang_chuyi_fix1-2025.3.25.1.dist-info/RECORD
